cellcog/__init__.py
cellcog/auth.py
cellcog/chat.py
cellcog/client.py
cellcog/config.py
cellcog/exceptions.py
cellcog/files.py
cellcog-0.1.1.dist-info/METADATA
cellcog-0.1.1.dist-info/WHEEL
cellcog-0.1.1.dist-info/licenses/LICENSE
cellcog-0.1.1.dist-info/RECORD
