Metadata-Version: 2.4
Name: cellcog
Version: 0.1.1
Summary: Python SDK for CellCog - Create complex multimodal content through AI orchestration
Project-URL: Homepage, https://cellcog.ai
Project-URL: Documentation, https://cellcog.ai/developer/docs
Project-URL: Repository, https://github.com/CellCog/cellcog_python
Project-URL: Issues, https://github.com/CellCog/cellcog_python/issues
Author-email: CellCog <support@cellcog.ai>
License: MIT
License-File: LICENSE
Keywords: ai,image,multimodal,openclaw,pdf,research,video
Classifier: Development Status :: 4 - Beta
Classifier: Intended Audience :: Developers
Classifier: License :: OSI Approved :: MIT License
Classifier: Programming Language :: Python :: 3
Classifier: Programming Language :: Python :: 3.9
Classifier: Programming Language :: Python :: 3.10
Classifier: Programming Language :: Python :: 3.11
Classifier: Programming Language :: Python :: 3.12
Classifier: Topic :: Scientific/Engineering :: Artificial Intelligence
Requires-Python: >=3.9
Requires-Dist: requests>=2.28.0
Provides-Extra: dev
Requires-Dist: black>=23.0.0; extra == 'dev'
Requires-Dist: pytest-asyncio>=0.21.0; extra == 'dev'
Requires-Dist: pytest>=7.0.0; extra == 'dev'
Requires-Dist: ruff>=0.1.0; extra == 'dev'
